{"rawWorkspaceDir": "${JENKINS_HOME}/workspace/${ITEM_FULLNAME}", "rawBuildsDir": "${ITEM_ROOTDIR}/builds", "system_message": "", "": "", "jenkins-model-MasterBuildConfiguration": {"numExecutors": "2"}, "jenkins-model-GlobalQuietPeriodConfiguration": {"quietPeriod": "5"}, "jenkins-model-GlobalSCMRetryCountConfiguration": {"scmCheckoutRetryCount": "0"}, "jenkins-model-GlobalProjectNamingStrategyConfiguration": {}, "jenkins-model-GlobalNodePropertiesConfiguration": {"globalNodeProperties": {}}, "jenkins-mvn-GlobalMavenConfig": {"": ["0", "0"], "settingsProvider": {"stapler-class": "jenkins.mvn.DefaultSettingsProvider"}, "globalSettingsProvider": {"stapler-class": "jenkins.mvn.DefaultGlobalSettingsProvider"}}, "hudson-model-JDK": {"tool": {"name": "JAVA_HOME", "home": "${JAVA_HOME}", "properties": {"stapler-class-bag": "true"}}}, "hudson-plugins-git-GitTool": {"tool": {"name": "Default", "home": "git.exe", "properties": {"stapler-class-bag": "true"}, "stapler-class": "hudson.plugins.git.GitTool", "kind": "hudson.plugins.git.GitTool"}}, "hudson-tasks-Maven$MavenInstallation": {"tool": {"name": "MAVEN_HOME", "home": "${M2_HOME}", "properties": {"stapler-class-bag": "true"}}}, "hudson-maven-MavenModuleSet": {"globalMavenOpts": "", "": "0", "localRepository": {"stapler-class": "hudson.maven.local_repo.DefaultLocalRepositoryLocator"}}, "hudson-model-UsageStatistics": {"usageStatisticsCollected": {}}, "jenkins-model-JenkinsLocationConfiguration": {"url": "http://172.16.27.152:3579/ci/", "adminAddress": "address not configured yet <nobody@nowhere>"}, "org-jenkinsci-main-modules-sshd-SSHD": {"port": {"value": "", "type": "random"}}, "hudson-plugins-collabnet-share-TeamForgeShare": {}, "hudson-plugins-git-GitSCM": {"globalConfigName": "", "globalConfigEmail": "", "createAccountBasedOnEmail": false}, "hudson-plugins-tfs-TeamFoundationServerScm": {"tfExecutable": "tfs"}, "hudson-scm-CVSSCM": {"cvsCompression": "3", "privateKeyLocation": "C:\\Documents and Settings\\Jagadeesh_r/.ssh/id_rsa", "privateKeyPassword": "vH6G4/JJ/zzhh5MfEJmzVQ==", "knownHostsLocation": "C:\\Documents and Settings\\Jagadeesh_r/.ssh/known_hosts"}, "hudson-scm-SubversionSCM": {"workspaceFormat": "8", "global_excluded_revprop": "", "storeAuthToDisk": {}}, "hudson-tasks-Shell": {"shell": ""}, "com-myyearbook-hudson-plugins-confluence-ConfluencePublisher": {"sites": {"url": "http://localhost/", "username": "admin", "password": "oLu4j39dGC3NqX1iMKigs8g4IuoSl7fBFguQp2RZKWc="}}, "hudson-plugins-emailext-ExtendedEmailPublisher": {"ext_mailer_default_content_type": "text/plain", "ext_mailer_default_recipients": "", "ext_mailer_emergency_reroute": "", "ext_mailer_default_subject": "$PROJECT_NAME - Build # $BUILD_NUMBER - $BUILD_STATUS!", "ext_mailer_max_attachment_size": "", "ext_mailer_default_body": "$PROJECT_NAME - Build # $BUILD_NUMBER - $BUILD_STATUS:\nCheck console output at $BUILD_URL to view the results."}, "hudson-tasks-Mailer": {"smtpServer": "smtp.gmail.com", "defaultSuffix": "", "useSsl": false, "smtpPort": "465", "replyToAddress": "", "charset": "UTF-8"}, "testflight-TestflightRecorder": {"tokenPair": {"tokenPairName": "testing11", "apiToken": "LHovXh+ze73K2MKHQ1ediYd+3Pj/EojR4B+3T8vMcaU=", "teamToken": "52L4mI9FZrAi51xTJYPvlfLN5i7GE/dGx0ZOdIvK4fw="}}, "com-cloudbees-jenkins-GitHubPushTrigger": {"hookMode": {"value": "none"}}, "core:apply": ""}